{
    "patent_id": "CN120257470A",
    "title": "CN120257470A - 面向低空典型场景的飞行器驾驶舱模拟方法及设备 - Google Patents",
    "status": "Unknown",
    "assignee": "Jiangsu Saizhong Technology Co ltd",
    "inventor": "",
    "url": "https://patents.google.com/patent/CN120257470A/zh",
    "citations": [],
    "cited_by": [
        {
            "Publication Number": "CN120469587A (zh) *",
            "Priority Date": "2025-07-14",
            "Publication Date": "2025-08-12",
            "Assignee": "杭州开临文化科技有限公司",
            "Title": "一种基于多模态感知的vr大空间定位交互系统",
            "Link": "https://patents.google.com/patent/CN120469587A/zh"
        },
        {
            "Publication Number": "CN120469587B (zh) *",
            "Priority Date": "2025-07-14",
            "Publication Date": "2025-09-12",
            "Assignee": "杭州开临文化科技有限公司",
            "Title": "一种基于多模态感知的vr大空间定位交互系统",
            "Link": "https://patents.google.com/patent/CN120469587B/zh"
        }
    ],
    "similar_documents": [],
    "last_updated": "2025-12-23 11:27:13"
}